src/com/PathIdentifier.py
src/com/__init__.py
zcrm_python_cl-0.0.3.dist-info/DESCRIPTION.rst
zcrm_python_cl-0.0.3.dist-info/METADATA
zcrm_python_cl-0.0.3.dist-info/RECORD
zcrm_python_cl-0.0.3.dist-info/WHEEL
zcrm_python_cl-0.0.3.dist-info/metadata.json
zcrm_python_cl-0.0.3.dist-info/top_level.txt
